{
    "pageNumber": 1,
    "pageSize": 100,
    "total": 7,
    "classes": [
        {
            "quarter": "20234",
            "courseId": "EACS     21  ",
            "title": "ZEN BUDDHISM",
            "contactHours": 30.0,
            "description": "An introduction to the history and texts of the major lineages of Ch`an Buddhism in China and Zen Buddhism in Japan.",
            "college": "L&S",
            "objLevelCode": "U",
            "subjectArea": "EACS    ",
            "unitsFixed": 4.0,
            "unitsVariableHigh": null,
            "unitsVariableLow": null,
            "delayedSectioning": null,
            "inProgressCourse": null,
            "gradingOption": null,
            "instructionType": "LEC",
            "onLineCourse": false,
            "deptCode": "EALCS",
            "generalEducation": [
                {
                    "geCode": "E  ",
                    "geCollege": "L&S "
                },
                {
                    "geCode": "NWC",
                    "geCollege": "L&S "
                },
                {
                    "geCode": "WRT",
                    "geCollege": "L&S "
                },
                {
                    "geCode": "E  ",
                    "geCollege": "ENGR"
                },
                {
                    "geCode": "WRT",
                    "geCollege": "ENGR"
                },
                {
                    "geCode": "NWC",
                    "geCollege": "ENGR"
                }
            ],
            "classSections": [
                {
                    "enrollCode": "10959",
                    "section": "0100",
                    "session": null,
                    "classClosed": null,
                    "courseCancelled": null,
                    "gradingOptionCode": null,
                    "enrolledTotal": 118,
                    "maxEnroll": 120,
                    "secondaryStatus": "R",
                    "departmentApprovalRequired": false,
                    "instructorApprovalRequired": false,
                    "restrictionLevel": null,
                    "restrictionMajor": null,
                    "restrictionMajorPass": null,
                    "restrictionMinor": null,
                    "restrictionMinorPass": null,
                    "concurrentCourses": [
                        "RG ST    21  0100"
                    ],
                    "timeLocations": [
                        {
                            "room": "HALL",
                            "building": "EMBAR",
                            "roomCapacity": 247,
                            "days": "M W    ",
                            "beginTime": "12:30",
                            "endTime": "13:45"
                        }
                    ],
                    "instructors": [
                        {
                            "instructor": "HILLIS G A",
                            "functionCode": "Teaching and in charge"
                        }
                    ]
                },
                {
                    "enrollCode": "10991",
                    "section": "0101",
                    "session": null,
                    "classClosed": null,
                    "courseCancelled": null,
                    "gradingOptionCode": null,
                    "enrolledTotal": 10,
                    "maxEnroll": 10,
                    "secondaryStatus": null,
                    "departmentApprovalRequired": false,
                    "instructorApprovalRequired": false,
                    "restrictionLevel": null,
                    "restrictionMajor": null,
                    "restrictionMajorPass": null,
                    "restrictionMinor": null,
                    "restrictionMinorPass": null,
                    "concurrentCourses": [
                        "RG ST    21  0101"
                    ],
                    "timeLocations": [
                        {
                            "room": "1232",
                            "building": "HSSB",
                            "roomCapacity": 20,
                            "days": " T     ",
                            "beginTime": "16:00",
                            "endTime": "16:50"
                        }
                    ],
                    "instructors": [
                        {
                            "instructor": "MA Y",
                            "functionCode": "Teaching but not in charge"
                        }
                    ]
                },
                {
                    "enrollCode": "11007",
                    "section": "0102",
                    "session": null,
                    "classClosed": null,
                    "courseCancelled": null,
                    "gradingOptionCode": null,
                    "enrolledTotal": 9,
                    "maxEnroll": 10,
                    "secondaryStatus": null,
                    "departmentApprovalRequired": false,
                    "instructorApprovalRequired": false,
                    "restrictionLevel": null,
                    "restrictionMajor": null,
                    "restrictionMajorPass": null,
                    "restrictionMinor": null,
                    "restrictionMinorPass": null,
                    "concurrentCourses": [
                        "RG ST    21  0102"
                    ],
                    "timeLocations": [
                        {
                            "room": "1227",
                            "building": "HSSB",
                            "roomCapacity": 20,
                            "days": " T     ",
                            "beginTime": "17:00",
                            "endTime": "17:50"
                        }
                    ],
                    "instructors": [
                        {
                            "instructor": "MA Y",
                            "functionCode": "Teaching but not in charge"
                        }
                    ]
                },
                {
                    "enrollCode": "11015",
                    "section": "0103",
                    "session": null,
                    "classClosed": null,
                    "courseCancelled": null,
                    "gradingOptionCode": null,
                    "enrolledTotal": 11,
                    "maxEnroll": 10,
                    "secondaryStatus": null,
                    "departmentApprovalRequired": false,
                    "instructorApprovalRequired": false,
                    "restrictionLevel": null,
                    "restrictionMajor": null,
                    "restrictionMajorPass": null,
                    "restrictionMinor": null,
                    "restrictionMinorPass": null,
                    "concurrentCourses": [
                        "RG ST    21  0103"
                    ],
                    "timeLocations": [
                        {
                            "room": "3001E",
                            "building": "HSSB",
                            "roomCapacity": null,
                            "days": " T     ",
                            "beginTime": "18:00",
                            "endTime": "18:50"
                        }
                    ],
                    "instructors": [
                        {
                            "instructor": "MA Y",
                            "functionCode": "Teaching but not in charge"
                        }
                    ]
                },
                {
                    "enrollCode": "11023",
                    "section": "0104",
                    "session": null,
                    "classClosed": null,
                    "courseCancelled": null,
                    "gradingOptionCode": null,
                    "enrolledTotal": 10,
                    "maxEnroll": 10,
                    "secondaryStatus": null,
                    "departmentApprovalRequired": false,
                    "instructorApprovalRequired": false,
                    "restrictionLevel": null,
                    "restrictionMajor": null,
                    "restrictionMajorPass": null,
                    "restrictionMinor": null,
                    "restrictionMinorPass": null,
                    "concurrentCourses": [
                        "RG ST    21  0104"
                    ],
                    "timeLocations": [
                        {
                            "room": "1210",
                            "building": "HSSB",
                            "roomCapacity": 20,
                            "days": "  W    ",
                            "beginTime": "16:00",
                            "endTime": "16:50"
                        }
                    ],
                    "instructors": [
                        {
                            "instructor": "CONNOR C V",
                            "functionCode": "Teaching and in charge"
                        }
                    ]
                },
                {
                    "enrollCode": "11031",
                    "section": "0105",
                    "session": null,
                    "classClosed": null,
                    "courseCancelled": null,
                    "gradingOptionCode": null,
                    "enrolledTotal": 9,
                    "maxEnroll": 10,
                    "secondaryStatus": null,
                    "departmentApprovalRequired": false,
                    "instructorApprovalRequired": false,
                    "restrictionLevel": null,
                    "restrictionMajor": null,
                    "restrictionMajorPass": null,
                    "restrictionMinor": null,
                    "restrictionMinorPass": null,
                    "concurrentCourses": [
                        "RG ST    21  0105"
                    ],
                    "timeLocations": [
                        {
                            "room": "1211",
                            "building": "HSSB",
                            "roomCapacity": 20,
                            "days": "  W    ",
                            "beginTime": "17:00",
                            "endTime": "17:50"
                        }
                    ],
                    "instructors": [
                        {
                            "instructor": "CONNOR C V",
                            "functionCode": "Teaching and in charge"
                        }
                    ]
                },
                {
                    "enrollCode": "11049",
                    "section": "0106",
                    "session": null,
                    "classClosed": null,
                    "courseCancelled": null,
                    "gradingOptionCode": null,
                    "enrolledTotal": 10,
                    "maxEnroll": 10,
                    "secondaryStatus": null,
                    "departmentApprovalRequired": false,
                    "instructorApprovalRequired": false,
                    "restrictionLevel": null,
                    "restrictionMajor": null,
                    "restrictionMajorPass": null,
                    "restrictionMinor": null,
                    "restrictionMinorPass": null,
                    "concurrentCourses": [
                        "RG ST    21  0106"
                    ],
                    "timeLocations": [
                        {
                            "room": "1206",
                            "building": "HSSB",
                            "roomCapacity": 20,
                            "days": "  W    ",
                            "beginTime": "18:00",
                            "endTime": "18:50"
                        }
                    ],
                    "instructors": [
                        {
                            "instructor": "CONNOR C V",
                            "functionCode": "Teaching and in charge"
                        }
                    ]
                },
                {
                    "enrollCode": "11056",
                    "section": "0107",
                    "session": null,
                    "classClosed": null,
                    "courseCancelled": null,
                    "gradingOptionCode": null,
                    "enrolledTotal": 10,
                    "maxEnroll": 10,
                    "secondaryStatus": null,
                    "departmentApprovalRequired": false,
                    "instructorApprovalRequired": false,
                    "restrictionLevel": null,
                    "restrictionMajor": null,
                    "restrictionMajorPass": null,
                    "restrictionMinor": null,
                    "restrictionMinorPass": null,
                    "concurrentCourses": [
                        "RG ST    21  0107"
                    ],
                    "timeLocations": [
                        {
                            "room": "1227",
                            "building": "HSSB",
                            "roomCapacity": 20,
                            "days": "   R   ",
                            "beginTime": "17:00",
                            "endTime": "17:50"
                        }
                    ],
                    "instructors": [
                        {
                            "instructor": "SERRANO A J",
                            "functionCode": "Teaching but not in charge"
                        }
                    ]
                },
                {
                    "enrollCode": "11064",
                    "section": "0108",
                    "session": null,
                    "classClosed": null,
                    "courseCancelled": null,
                    "gradingOptionCode": null,
                    "enrolledTotal": 8,
                    "maxEnroll": 10,
                    "secondaryStatus": null,
                    "departmentApprovalRequired": false,
                    "instructorApprovalRequired": false,
                    "restrictionLevel": null,
                    "restrictionMajor": null,
                    "restrictionMajorPass": null,
                    "restrictionMinor": null,
                    "restrictionMinorPass": null,
                    "concurrentCourses": [
                        "RG ST    21  0108"
                    ],
                    "timeLocations": [
                        {
                            "room": "2252",
                            "building": "HSSB",
                            "roomCapacity": null,
                            "days": "   R   ",
                            "beginTime": "18:00",
                            "endTime": "18:50"
                        }
                    ],
                    "instructors": [
                        {
                            "instructor": "SERRANO A J",
                            "functionCode": "Teaching but not in charge"
                        }
                    ]
                },
                {
                    "enrollCode": "11072",
                    "section": "0109",
                    "session": null,
                    "classClosed": null,
                    "courseCancelled": null,
                    "gradingOptionCode": null,
                    "enrolledTotal": 9,
                    "maxEnroll": 10,
                    "secondaryStatus": null,
                    "departmentApprovalRequired": false,
                    "instructorApprovalRequired": false,
                    "restrictionLevel": null,
                    "restrictionMajor": null,
                    "restrictionMajorPass": null,
                    "restrictionMinor": null,
                    "restrictionMinorPass": null,
                    "concurrentCourses": [
                        "RG ST    21  0109"
                    ],
                    "timeLocations": [
                        {
                            "room": "1210",
                            "building": "HSSB",
                            "roomCapacity": 20,
                            "days": "   R   ",
                            "beginTime": "19:00",
                            "endTime": "19:50"
                        }
                    ],
                    "instructors": [
                        {
                            "instructor": "SERRANO A J",
                            "functionCode": "Teaching but not in charge"
                        }
                    ]
                },
                {
                    "enrollCode": "11080",
                    "section": "0110",
                    "session": null,
                    "classClosed": null,
                    "courseCancelled": null,
                    "gradingOptionCode": null,
                    "enrolledTotal": 10,
                    "maxEnroll": 10,
                    "secondaryStatus": null,
                    "departmentApprovalRequired": false,
                    "instructorApprovalRequired": false,
                    "restrictionLevel": null,
                    "restrictionMajor": null,
                    "restrictionMajorPass": null,
                    "restrictionMinor": null,
                    "restrictionMinorPass": null,
                    "concurrentCourses": [
                        "RG ST    21  0110"
                    ],
                    "timeLocations": [
                        {
                            "room": "1207",
                            "building": "HSSB",
                            "roomCapacity": 20,
                            "days": "    F  ",
                            "beginTime": "10:00",
                            "endTime": "10:50"
                        }
                    ],
                    "instructors": [
                        {
                            "instructor": "GODDARD E L",
                            "functionCode": "Teaching but not in charge"
                        }
                    ]
                },
                {
                    "enrollCode": "11098",
                    "section": "0111",
                    "session": null,
                    "classClosed": null,
                    "courseCancelled": null,
                    "gradingOptionCode": null,
                    "enrolledTotal": 10,
                    "maxEnroll": 10,
                    "secondaryStatus": null,
                    "departmentApprovalRequired": false,
                    "instructorApprovalRequired": false,
                    "restrictionLevel": null,
                    "restrictionMajor": null,
                    "restrictionMajorPass": null,
                    "restrictionMinor": null,
                    "restrictionMinorPass": null,
                    "concurrentCourses": [
                        "RG ST    21  0111"
                    ],
                    "timeLocations": [
                        {
                            "room": "1215",
                            "building": "HSSB",
                            "roomCapacity": 20,
                            "days": "    F  ",
                            "beginTime": "11:00",
                            "endTime": "11:50"
                        }
                    ],
                    "instructors": [
                        {
                            "instructor": "GODDARD E L",
                            "functionCode": "Teaching but not in charge"
                        }
                    ]
                },
                {
                    "enrollCode": "11106",
                    "section": "0112",
                    "session": null,
                    "classClosed": null,
                    "courseCancelled": null,
                    "gradingOptionCode": null,
                    "enrolledTotal": 12,
                    "maxEnroll": 10,
                    "secondaryStatus": null,
                    "departmentApprovalRequired": false,
                    "instructorApprovalRequired": false,
                    "restrictionLevel": null,
                    "restrictionMajor": null,
                    "restrictionMajorPass": null,
                    "restrictionMinor": null,
                    "restrictionMinorPass": null,
                    "concurrentCourses": [
                        "RG ST    21  0112"
                    ],
                    "timeLocations": [
                        {
                            "room": "2252",
                            "building": "HSSB",
                            "roomCapacity": null,
                            "days": "    F  ",
                            "beginTime": "12:00",
                            "endTime": "12:50"
                        }
                    ],
                    "instructors": [
                        {
                            "instructor": "GODDARD E L",
                            "functionCode": "Teaching but not in charge"
                        }
                    ]
                }
            ]
        },
        {
            "quarter": "20234",
            "courseId": "EACS     99RA",
            "title": "INDEP RESEARCH ASST",
            "contactHours": 10.0,
            "description": "Research details are decided by the supervising Professor in   the Department of East Asian Languages and Cultural Studies.",
            "college": "L&S",
            "objLevelCode": "U",
            "subjectArea": "EACS    ",
            "unitsFixed": null,
            "unitsVariableHigh": 4.0,
            "unitsVariableLow": 1.0,
            "delayedSectioning": "Y",
            "inProgressCourse": null,
            "gradingOption": null,
            "instructionType": "TUT",
            "onLineCourse": false,
            "deptCode": "EALCS",
            "generalEducation": [],
            "classSections": [
                {
                    "enrollCode": "11114",
                    "section": "0100",
                    "session": null,
                    "classClosed": null,
                    "courseCancelled": null,
                    "gradingOptionCode": null,
                    "enrolledTotal": null,
                    "maxEnroll": null,
                    "secondaryStatus": null,
                    "departmentApprovalRequired": false,
                    "instructorApprovalRequired": true,
                    "restrictionLevel": null,
                    "restrictionMajor": null,
                    "restrictionMajorPass": null,
                    "restrictionMinor": null,
                    "restrictionMinorPass": null,
                    "concurrentCourses": [],
                    "timeLocations": [],
                    "instructors": []
                }
            ]
        },
        {
            "quarter": "20234",
            "courseId": "EACS    103B ",
            "title": "ANTHRO OF JAPAN",
            "contactHours": 30.0,
            "description": "This course examines Japan as depicted in contemporary ethnography. We cons ider how Japan has been imagined as a distinct culture by exploring gender, religion, family structures, the education system, the environment, manage ment of difference, globalization and domestication, immigration, and moder nization.",
            "college": "L&S",
            "objLevelCode": "U",
            "subjectArea": "EACS    ",
            "unitsFixed": 4.0,
            "unitsVariableHigh": null,
            "unitsVariableLow": null,
            "delayedSectioning": null,
            "inProgressCourse": null,
            "gradingOption": null,
            "instructionType": "LEC",
            "onLineCourse": false,
            "deptCode": "EALCS",
            "generalEducation": [
                {
                    "geCode": "D  ",
                    "geCollege": "L&S "
                },
                {
                    "geCode": "D  ",
                    "geCollege": "ENGR"
                },
                {
                    "geCode": "NWC",
                    "geCollege": "L&S "
                },
                {
                    "geCode": "NWC",
                    "geCollege": "ENGR"
                }
            ],
            "classSections": [
                {
                    "enrollCode": "52662",
                    "section": "0100",
                    "session": null,
                    "classClosed": null,
                    "courseCancelled": null,
                    "gradingOptionCode": null,
                    "enrolledTotal": 68,
                    "maxEnroll": 75,
                    "secondaryStatus": null,
                    "departmentApprovalRequired": false,
                    "instructorApprovalRequired": false,
                    "restrictionLevel": "U",
                    "restrictionMajor": null,
                    "restrictionMajorPass": null,
                    "restrictionMinor": null,
                    "restrictionMinorPass": null,
                    "concurrentCourses": [],
                    "timeLocations": [
                        {
                            "room": "1260",
                            "building": "PHELP",
                            "roomCapacity": 90,
                            "days": "M W    ",
                            "beginTime": "12:30",
                            "endTime": "13:45"
                        }
                    ],
                    "instructors": [
                        {
                            "instructor": "IKEUCHI S",
                            "functionCode": "Teaching and in charge"
                        }
                    ]
                }
            ]
        },
        {
            "quarter": "20234",
            "courseId": "EACS    131  ",
            "title": "GLOBAL EAST ASIA",
            "contactHours": 30.0,
            "description": "Offers an overview of theories about migration and globalization, coupled w ith the case studies from contemporary East Asia. Students investigate dive rse transnational issues in and from this region, including ethnicity, nati onalism, kinship, homeland, and colonialism.",
            "college": "L&S",
            "objLevelCode": "U",
            "subjectArea": "EACS    ",
            "unitsFixed": 4.0,
            "unitsVariableHigh": null,
            "unitsVariableLow": null,
            "delayedSectioning": null,
            "inProgressCourse": null,
            "gradingOption": null,
            "instructionType": "LEC",
            "onLineCourse": false,
            "deptCode": "EALCS",
            "generalEducation": [],
            "classSections": [
                {
                    "enrollCode": "52670",
                    "section": "0100",
                    "session": null,
                    "classClosed": null,
                    "courseCancelled": null,
                    "gradingOptionCode": null,
                    "enrolledTotal": 33,
                    "maxEnroll": 35,
                    "secondaryStatus": null,
                    "departmentApprovalRequired": false,
                    "instructorApprovalRequired": false,
                    "restrictionLevel": "U",
                    "restrictionMajor": null,
                    "restrictionMajorPass": null,
                    "restrictionMinor": null,
                    "restrictionMinorPass": null,
                    "concurrentCourses": [],
                    "timeLocations": [
                        {
                            "room": "1440",
                            "building": "PHELP",
                            "roomCapacity": 35,
                            "days": "M W    ",
                            "beginTime": "11:00",
                            "endTime": "12:15"
                        }
                    ],
                    "instructors": [
                        {
                            "instructor": "IKEUCHI S",
                            "functionCode": "Teaching and in charge"
                        }
                    ]
                }
            ]
        },
        {
            "quarter": "20234",
            "courseId": "EACS    132  ",
            "title": "ASIA SOC MOVEMTS",
            "contactHours": 30.0,
            "description": "This course engages with cultural histories of social movements and political protests in modern and contemporary East Asia. All reading, viewing, and listening material will be available in English translation.",
            "college": "L&S",
            "objLevelCode": "U",
            "subjectArea": "EACS    ",
            "unitsFixed": 4.0,
            "unitsVariableHigh": null,
            "unitsVariableLow": null,
            "delayedSectioning": null,
            "inProgressCourse": null,
            "gradingOption": null,
            "instructionType": "LEC",
            "onLineCourse": false,
            "deptCode": "EALCS",
            "generalEducation": [],
            "classSections": [
                {
                    "enrollCode": "61879",
                    "section": "0100",
                    "session": null,
                    "classClosed": null,
                    "courseCancelled": null,
                    "gradingOptionCode": null,
                    "enrolledTotal": 36,
                    "maxEnroll": 45,
                    "secondaryStatus": null,
                    "departmentApprovalRequired": false,
                    "instructorApprovalRequired": false,
                    "restrictionLevel": "U",
                    "restrictionMajor": null,
                    "restrictionMajorPass": null,
                    "restrictionMinor": null,
                    "restrictionMinorPass": null,
                    "concurrentCourses": [],
                    "timeLocations": [
                        {
                            "room": "1109",
                            "building": "NH",
                            "roomCapacity": 48,
                            "days": "M W    ",
                            "beginTime": "14:00",
                            "endTime": "15:15"
                        }
                    ],
                    "instructors": [
                        {
                            "instructor": "HWANG S",
                            "functionCode": "Teaching and in charge"
                        }
                    ]
                }
            ]
        },
        {
            "quarter": "20234",
            "courseId": "EACS    141  ",
            "title": "ENV JUSTICE IN ASIA",
            "contactHours": 30.0,
            "description": "Applies environmental justice, a tool for addressing social   and ethnic/racial inequality in environmental conditions, to   analysis of Asia. Contrasts mainstream environmental and   sustainability models with the justice-based approach to   analyze how local communities devise solutions for   environmental crises.",
            "college": "L&S",
            "objLevelCode": "U",
            "subjectArea": "EACS    ",
            "unitsFixed": 4.0,
            "unitsVariableHigh": null,
            "unitsVariableLow": null,
            "delayedSectioning": null,
            "inProgressCourse": null,
            "gradingOption": "L",
            "instructionType": "LEC",
            "onLineCourse": false,
            "deptCode": "EALCS",
            "generalEducation": [],
            "classSections": [
                {
                    "enrollCode": "54890",
                    "section": "0100",
                    "session": null,
                    "classClosed": "Y",
                    "courseCancelled": null,
                    "gradingOptionCode": null,
                    "enrolledTotal": null,
                    "maxEnroll": 45,
                    "secondaryStatus": null,
                    "departmentApprovalRequired": false,
                    "instructorApprovalRequired": false,
                    "restrictionLevel": "U",
                    "restrictionMajor": null,
                    "restrictionMajorPass": null,
                    "restrictionMinor": null,
                    "restrictionMinorPass": null,
                    "concurrentCourses": [],
                    "timeLocations": [
                        {
                            "room": "1109",
                            "building": "NH",
                            "roomCapacity": 48,
                            "days": "M W    ",
                            "beginTime": "14:00",
                            "endTime": "15:15"
                        }
                    ],
                    "instructors": [
                        {
                            "instructor": "HWANG S",
                            "functionCode": "Teaching and in charge"
                        }
                    ]
                }
            ]
        },
        {
            "quarter": "20234",
            "courseId": "EACS    199  ",
            "title": "INDEPENDENT STUDY",
            "contactHours": 10.0,
            "description": "Independent Study under the supervision of a faculty member.",
            "college": "L&S",
            "objLevelCode": "U",
            "subjectArea": "EACS    ",
            "unitsFixed": null,
            "unitsVariableHigh": 5.0,
            "unitsVariableLow": 1.0,
            "delayedSectioning": "Y",
            "inProgressCourse": null,
            "gradingOption": null,
            "instructionType": "TUT",
            "onLineCourse": false,
            "deptCode": "EALCS",
            "generalEducation": [],
            "classSections": [
                {
                    "enrollCode": "11130",
                    "section": "0100",
                    "session": null,
                    "classClosed": null,
                    "courseCancelled": null,
                    "gradingOptionCode": null,
                    "enrolledTotal": null,
                    "maxEnroll": 5,
                    "secondaryStatus": null,
                    "departmentApprovalRequired": true,
                    "instructorApprovalRequired": false,
                    "restrictionLevel": "U",
                    "restrictionMajor": null,
                    "restrictionMajorPass": null,
                    "restrictionMinor": null,
                    "restrictionMinorPass": null,
                    "concurrentCourses": [],
                    "timeLocations": [],
                    "instructors": []
                }
            ]
        }
    ]
}