{
    "pageNumber": 1,
    "pageSize": 100,
    "total": 4,
    "classes": [
        {
            "quarter": "20233",
            "courseId": "CHIN     40  ",
            "title": "CHINESE POP CULTURE",
            "contactHours": 30.0,
            "description": "Provides an overview of Chinese popular culture from PRC, Taiwan, and Hong Kong, covering various media and genres such as popular literature, film, o nline culture, music, video games, and cartoons.",
            "college": "L&S",
            "objLevelCode": "U",
            "subjectArea": "CHIN    ",
            "unitsFixed": 4.0,
            "unitsVariableHigh": null,
            "unitsVariableLow": null,
            "delayedSectioning": null,
            "inProgressCourse": null,
            "gradingOption": null,
            "instructionType": "LEC",
            "onLineCourse": false,
            "deptCode": "EALCS",
            "generalEducation": [
                {
                    "geCode": "NWC",
                    "geCollege": "L&S "
                },
                {
                    "geCode": "WRT",
                    "geCollege": "L&S "
                },
                {
                    "geCode": "WRT",
                    "geCollege": "ENGR"
                },
                {
                    "geCode": "F  ",
                    "geCollege": "L&S "
                },
                {
                    "geCode": "F  ",
                    "geCollege": "ENGR"
                },
                {
                    "geCode": "NWC",
                    "geCollege": "ENGR"
                }
            ],
            "classSections": [
                {
                    "enrollCode": "17996",
                    "section": "0100",
                    "session": "00000B  ",
                    "classClosed": null,
                    "courseCancelled": null,
                    "gradingOptionCode": null,
                    "enrolledTotal": 54,
                    "maxEnroll": 60,
                    "secondaryStatus": "R",
                    "departmentApprovalRequired": false,
                    "instructorApprovalRequired": false,
                    "restrictionLevel": null,
                    "restrictionMajor": null,
                    "restrictionMajorPass": null,
                    "restrictionMinor": null,
                    "restrictionMinorPass": null,
                    "concurrentCourses": [],
                    "timeLocations": [
                        {
                            "room": "1425",
                            "building": "PHELP",
                            "roomCapacity": 65,
                            "days": "M W    ",
                            "beginTime": "15:30",
                            "endTime": "17:35"
                        }
                    ],
                    "instructors": [
                        {
                            "instructor": "LI X",
                            "functionCode": "Teaching and in charge"
                        }
                    ]
                },
                {
                    "enrollCode": "19067",
                    "section": "0101",
                    "session": "00000B  ",
                    "classClosed": null,
                    "courseCancelled": null,
                    "gradingOptionCode": null,
                    "enrolledTotal": 19,
                    "maxEnroll": 20,
                    "secondaryStatus": null,
                    "departmentApprovalRequired": false,
                    "instructorApprovalRequired": false,
                    "restrictionLevel": null,
                    "restrictionMajor": null,
                    "restrictionMajorPass": null,
                    "restrictionMinor": null,
                    "restrictionMinorPass": null,
                    "concurrentCourses": [],
                    "timeLocations": [
                        {
                            "room": "4201",
                            "building": "HSSB",
                            "roomCapacity": 24,
                            "days": "   R   ",
                            "beginTime": "11:00",
                            "endTime": "12:25"
                        }
                    ],
                    "instructors": [
                        {
                            "instructor": "CHANG L",
                            "functionCode": "Teaching but not in charge"
                        }
                    ]
                },
                {
                    "enrollCode": "19059",
                    "section": "0102",
                    "session": "00000B  ",
                    "classClosed": null,
                    "courseCancelled": null,
                    "gradingOptionCode": null,
                    "enrolledTotal": 17,
                    "maxEnroll": 20,
                    "secondaryStatus": null,
                    "departmentApprovalRequired": false,
                    "instructorApprovalRequired": false,
                    "restrictionLevel": null,
                    "restrictionMajor": null,
                    "restrictionMajorPass": null,
                    "restrictionMinor": null,
                    "restrictionMinorPass": null,
                    "concurrentCourses": [],
                    "timeLocations": [
                        {
                            "room": "4202",
                            "building": "HSSB",
                            "roomCapacity": 24,
                            "days": "   R   ",
                            "beginTime": "13:00",
                            "endTime": "14:25"
                        }
                    ],
                    "instructors": [
                        {
                            "instructor": "CHANG L",
                            "functionCode": "Teaching but not in charge"
                        }
                    ]
                },
                {
                    "enrollCode": "19075",
                    "section": "0103",
                    "session": "00000B  ",
                    "classClosed": null,
                    "courseCancelled": null,
                    "gradingOptionCode": null,
                    "enrolledTotal": 18,
                    "maxEnroll": 20,
                    "secondaryStatus": null,
                    "departmentApprovalRequired": false,
                    "instructorApprovalRequired": false,
                    "restrictionLevel": null,
                    "restrictionMajor": null,
                    "restrictionMajorPass": null,
                    "restrictionMinor": null,
                    "restrictionMinorPass": null,
                    "concurrentCourses": [],
                    "timeLocations": [
                        {
                            "room": "2252",
                            "building": "HSSB",
                            "roomCapacity": null,
                            "days": "   R   ",
                            "beginTime": "17:00",
                            "endTime": "18:25"
                        }
                    ],
                    "instructors": [
                        {
                            "instructor": "CHANG L",
                            "functionCode": "Teaching but not in charge"
                        }
                    ]
                }
            ]
        },
        {
            "quarter": "20233",
            "courseId": "CHIN     48  ",
            "title": "NATUR ETH CHIN PHIL",
            "contactHours": 30.0,
            "description": "A look at how major thinkers in classical Chinese thought grappled with que stions related to the individual's place in society and their relationship to their environment. Highlighting their relevance, classical views will be applied to contemporary ethical, social, and environmental debates.",
            "college": "L&S",
            "objLevelCode": "U",
            "subjectArea": "CHIN    ",
            "unitsFixed": 4.0,
            "unitsVariableHigh": null,
            "unitsVariableLow": null,
            "delayedSectioning": null,
            "inProgressCourse": null,
            "gradingOption": null,
            "instructionType": "LEC",
            "onLineCourse": false,
            "deptCode": "EALCS",
            "generalEducation": [
                {
                    "geCode": "E  ",
                    "geCollege": "L&S "
                },
                {
                    "geCode": "NWC",
                    "geCollege": "L&S "
                },
                {
                    "geCode": "WRT",
                    "geCollege": "L&S "
                },
                {
                    "geCode": "E  ",
                    "geCollege": "ENGR"
                },
                {
                    "geCode": "WRT",
                    "geCollege": "ENGR"
                }
            ],
            "classSections": [
                {
                    "enrollCode": "18010",
                    "section": "0100",
                    "session": "00000B  ",
                    "classClosed": null,
                    "courseCancelled": null,
                    "gradingOptionCode": null,
                    "enrolledTotal": 18,
                    "maxEnroll": 60,
                    "secondaryStatus": "R",
                    "departmentApprovalRequired": false,
                    "instructorApprovalRequired": false,
                    "restrictionLevel": null,
                    "restrictionMajor": null,
                    "restrictionMajorPass": null,
                    "restrictionMinor": null,
                    "restrictionMinorPass": null,
                    "concurrentCourses": [],
                    "timeLocations": [
                        {
                            "room": "2516",
                            "building": "PHELP",
                            "roomCapacity": 60,
                            "days": " TWR   ",
                            "beginTime": "17:00",
                            "endTime": "18:25"
                        }
                    ],
                    "instructors": [
                        {
                            "instructor": "STEAVU-BALINT",
                            "functionCode": "Teaching and in charge"
                        }
                    ]
                },
                {
                    "enrollCode": "19091",
                    "section": "0101",
                    "session": "00000B  ",
                    "classClosed": null,
                    "courseCancelled": null,
                    "gradingOptionCode": null,
                    "enrolledTotal": 4,
                    "maxEnroll": 20,
                    "secondaryStatus": null,
                    "departmentApprovalRequired": false,
                    "instructorApprovalRequired": false,
                    "restrictionLevel": null,
                    "restrictionMajor": null,
                    "restrictionMajorPass": null,
                    "restrictionMinor": null,
                    "restrictionMinorPass": null,
                    "concurrentCourses": [],
                    "timeLocations": [
                        {
                            "room": "2252",
                            "building": "HSSB",
                            "roomCapacity": null,
                            "days": "  W    ",
                            "beginTime": "13:00",
                            "endTime": "14:25"
                        }
                    ],
                    "instructors": [
                        {
                            "instructor": "FRIEDMAN U D",
                            "functionCode": "Teaching and in charge"
                        }
                    ]
                },
                {
                    "enrollCode": "19083",
                    "section": "0102",
                    "session": "00000B  ",
                    "classClosed": null,
                    "courseCancelled": null,
                    "gradingOptionCode": null,
                    "enrolledTotal": 1,
                    "maxEnroll": 20,
                    "secondaryStatus": null,
                    "departmentApprovalRequired": false,
                    "instructorApprovalRequired": false,
                    "restrictionLevel": null,
                    "restrictionMajor": null,
                    "restrictionMajorPass": null,
                    "restrictionMinor": null,
                    "restrictionMinorPass": null,
                    "concurrentCourses": [],
                    "timeLocations": [
                        {
                            "room": "2252",
                            "building": "HSSB",
                            "roomCapacity": null,
                            "days": "  W    ",
                            "beginTime": "14:30",
                            "endTime": "15:55"
                        }
                    ],
                    "instructors": [
                        {
                            "instructor": "FRIEDMAN U D",
                            "functionCode": "Teaching and in charge"
                        }
                    ]
                },
                {
                    "enrollCode": "19109",
                    "section": "0103",
                    "session": "00000B  ",
                    "classClosed": null,
                    "courseCancelled": null,
                    "gradingOptionCode": null,
                    "enrolledTotal": 13,
                    "maxEnroll": 20,
                    "secondaryStatus": null,
                    "departmentApprovalRequired": false,
                    "instructorApprovalRequired": false,
                    "restrictionLevel": null,
                    "restrictionMajor": null,
                    "restrictionMajorPass": null,
                    "restrictionMinor": null,
                    "restrictionMinorPass": null,
                    "concurrentCourses": [],
                    "timeLocations": [
                        {
                            "room": "2252",
                            "building": "HSSB",
                            "roomCapacity": null,
                            "days": "M      ",
                            "beginTime": "16:00",
                            "endTime": "17:25"
                        }
                    ],
                    "instructors": [
                        {
                            "instructor": "FRIEDMAN U D",
                            "functionCode": "Teaching and in charge"
                        }
                    ]
                }
            ]
        },
        {
            "quarter": "20233",
            "courseId": "CHIN    103  ",
            "title": "READ & WRT IN CHIN",
            "contactHours": 30.0,
            "description": "Designed to enhance reading and writing skills in Chinese for students who have finished second year Chinese.",
            "college": "L&S",
            "objLevelCode": "U",
            "subjectArea": "CHIN    ",
            "unitsFixed": 4.0,
            "unitsVariableHigh": null,
            "unitsVariableLow": null,
            "delayedSectioning": null,
            "inProgressCourse": null,
            "gradingOption": null,
            "instructionType": "LEC",
            "onLineCourse": false,
            "deptCode": "EALCS",
            "generalEducation": [],
            "classSections": [
                {
                    "enrollCode": "02410",
                    "section": "0100",
                    "session": "00000D  ",
                    "classClosed": null,
                    "courseCancelled": null,
                    "gradingOptionCode": null,
                    "enrolledTotal": 18,
                    "maxEnroll": 20,
                    "secondaryStatus": null,
                    "departmentApprovalRequired": false,
                    "instructorApprovalRequired": false,
                    "restrictionLevel": null,
                    "restrictionMajor": null,
                    "restrictionMajorPass": null,
                    "restrictionMinor": null,
                    "restrictionMinorPass": null,
                    "concurrentCourses": [],
                    "timeLocations": [
                        {
                            "room": "LINE",
                            "building": "ON",
                            "roomCapacity": 999,
                            "days": "MTWR   ",
                            "beginTime": "10:00",
                            "endTime": "12:05"
                        }
                    ],
                    "instructors": [
                        {
                            "instructor": "CHEN S C",
                            "functionCode": "Teaching and in charge"
                        }
                    ]
                }
            ]
        },
        {
            "quarter": "20233",
            "courseId": "CHIN    199  ",
            "title": "INDEPENDENT STUDIES",
            "contactHours": null,
            "description": "Independent studies in Chinese. Individual investigations in   literary fields.",
            "college": "L&S",
            "objLevelCode": "U",
            "subjectArea": "CHIN    ",
            "unitsFixed": null,
            "unitsVariableHigh": 5.0,
            "unitsVariableLow": 1.0,
            "delayedSectioning": "I",
            "inProgressCourse": null,
            "gradingOption": null,
            "instructionType": "TUT",
            "onLineCourse": false,
            "deptCode": "EALCS",
            "generalEducation": [],
            "classSections": [
                {
                    "enrollCode": "27144",
                    "section": "0100",
                    "session": null,
                    "classClosed": null,
                    "courseCancelled": null,
                    "gradingOptionCode": null,
                    "enrolledTotal": null,
                    "maxEnroll": 1,
                    "secondaryStatus": null,
                    "departmentApprovalRequired": false,
                    "instructorApprovalRequired": false,
                    "restrictionLevel": "U",
                    "restrictionMajor": null,
                    "restrictionMajorPass": null,
                    "restrictionMinor": null,
                    "restrictionMinorPass": null,
                    "concurrentCourses": [],
                    "timeLocations": [],
                    "instructors": []
                },
                {
                    "enrollCode": "27169",
                    "section": "0200",
                    "session": "00000B  ",
                    "classClosed": null,
                    "courseCancelled": null,
                    "gradingOptionCode": null,
                    "enrolledTotal": 1,
                    "maxEnroll": 1,
                    "secondaryStatus": null,
                    "departmentApprovalRequired": false,
                    "instructorApprovalRequired": false,
                    "restrictionLevel": "U",
                    "restrictionMajor": null,
                    "restrictionMajorPass": null,
                    "restrictionMinor": null,
                    "restrictionMinorPass": null,
                    "concurrentCourses": [],
                    "timeLocations": [],
                    "instructors": [
                        {
                            "instructor": "STEAVU-BALINT",
                            "functionCode": "Teaching and in charge"
                        }
                    ]
                }
            ]
        }
    ]
}